{"success":true,"message":null,"returnValue":[{"category_name":"洗衣机","year":"2017","province_name":"福建省","sales_count":350},{"category_name":"洗衣机","year":"2017","province_name":"重庆市","sales_count":255},{"category_name":"洗衣机","year":"2017","province_name":"内蒙古","sales_count":301},{"category_name":"洗衣机","year":"2017","province_name":"新疆区","sales_count":374},{"category_name":"洗衣机","year":"2017","province_name":"青海省","sales_count":302},{"category_name":"洗衣机","year":"2017","province_name":"江苏省","sales_count":323},{"category_name":"洗衣机","year":"2017","province_name":"湖南省","sales_count":365},{"category_name":"洗衣机","year":"2017","province_name":"安徽省","sales_count":339},{"category_name":"洗衣机","year":"2017","province_name":"湖北省","sales_count":244},{"category_name":"洗衣机","year":"2017","province_name":"云南省","sales_count":283},{"category_name":"洗衣机","year":"2017","province_name":"贵州省","sales_count":363},{"category_name":"洗衣机","year":"2017","province_name":"黑龙江省","sales_count":299},{"category_name":"洗衣机","year":"2017","province_name":"陕西省","sales_count":244},{"category_name":"洗衣机","year":"2017","province_name":"山西省","sales_count":236},{"category_name":"洗衣机","year":"2017","province_name":"甘肃省","sales_count":383},{"category_name":"洗衣机","year":"2017","province_name":"上海市","sales_count":300},{"category_name":"洗衣机","year":"2017","province_name":"天津市","sales_count":287},{"category_name":"洗衣机","year":"2017","province_name":"山东省","sales_count":386},{"category_name":"洗衣机","year":"2017","province_name":"四川省","sales_count":319},{"category_name":"洗衣机","year":"2017","province_name":"广东省","sales_count":274},{"category_name":"洗衣机","year":"2017","province_name":"浙江省","sales_count":239},{"category_name":"洗衣机","year":"2017","province_name":"江西省","sales_count":382},{"category_name":"洗衣机","year":"2017","province_name":"辽宁省","sales_count":342},{"category_name":"洗衣机","year":"2017","province_name":"河南省","sales_count":363},{"category_name":"洗衣机","year":"2017","province_name":"吉林省","sales_count":341},{"category_name":"洗衣机","year":"2017","province_name":"北京市","sales_count":245},{"category_name":"洗衣机","year":"2017","province_name":"海南省","sales_count":378},{"category_name":"洗衣机","year":"2017","province_name":"宁夏区","sales_count":338},{"category_name":"洗衣机","year":"2017","province_name":"西藏区","sales_count":261},{"category_name":"洗衣机","year":"2017","province_name":"河北省","sales_count":261},{"category_name":"洗衣机","year":"2017","province_name":"广西壮族自治区","sales_count":346},{"category_name":"冰箱","year":"2017","province_name":"福建省","sales_count":223},{"category_name":"冰箱","year":"2017","province_name":"重庆市","sales_count":281},{"category_name":"冰箱","year":"2017","province_name":"内蒙古","sales_count":292},{"category_name":"冰箱","year":"2017","province_name":"新疆区","sales_count":278},{"category_name":"冰箱","year":"2017","province_name":"青海省","sales_count":345},{"category_name":"冰箱","year":"2017","province_name":"江苏省","sales_count":263},{"category_name":"冰箱","year":"2017","province_name":"湖南省","sales_count":208},{"category_name":"冰箱","year":"2017","province_name":"安徽省","sales_count":313},{"category_name":"冰箱","year":"2017","province_name":"湖北省","sales_count":222},{"category_name":"冰箱","year":"2017","province_name":"云南省","sales_count":358},{"category_name":"冰箱","year":"2017","province_name":"贵州省","sales_count":376},{"category_name":"冰箱","year":"2017","province_name":"黑龙江省","sales_count":320},{"category_name":"冰箱","year":"2017","province_name":"陕西省","sales_count":325},{"category_name":"冰箱","year":"2017","province_name":"山西省","sales_count":339},{"category_name":"冰箱","year":"2017","province_name":"甘肃省","sales_count":293},{"category_name":"冰箱","year":"2017","province_name":"上海市","sales_count":223},{"category_name":"冰箱","year":"2017","province_name":"天津市","sales_count":336},{"category_name":"冰箱","year":"2017","province_name":"山东省","sales_count":324},{"category_name":"冰箱","year":"2017","province_name":"四川省","sales_count":357},{"category_name":"冰箱","year":"2017","province_name":"广东省","sales_count":233},{"category_name":"冰箱","year":"2017","province_name":"浙江省","sales_count":287},{"category_name":"冰箱","year":"2017","province_name":"江西省","sales_count":310},{"category_name":"冰箱","year":"2017","province_name":"辽宁省","sales_count":272},{"category_name":"冰箱","year":"2017","province_name":"河南省","sales_count":255},{"category_name":"冰箱","year":"2017","province_name":"吉林省","sales_count":368},{"category_name":"冰箱","year":"2017","province_name":"北京市","sales_count":239},{"category_name":"冰箱","year":"2017","province_name":"海南省","sales_count":263},{"category_name":"冰箱","year":"2017","province_name":"宁夏区","sales_count":378},{"category_name":"冰箱","year":"2017","province_name":"西藏区","sales_count":321},{"category_name":"冰箱","year":"2017","province_name":"河北省","sales_count":231},{"category_name":"冰箱","year":"2017","province_name":"广西壮族自治区","sales_count":270},{"category_name":"壁挂炉","year":"2017","province_name":"福建省","sales_count":272},{"category_name":"壁挂炉","year":"2017","province_name":"重庆市","sales_count":394},{"category_name":"壁挂炉","year":"2017","province_name":"内蒙古","sales_count":273},{"category_name":"壁挂炉","year":"2017","province_name":"新疆区","sales_count":251},{"category_name":"壁挂炉","year":"2017","province_name":"青海省","sales_count":278},{"category_name":"壁挂炉","year":"2017","province_name":"江苏省","sales_count":364},{"category_name":"壁挂炉","year":"2017","province_name":"湖南省","sales_count":339},{"category_name":"壁挂炉","year":"2017","province_name":"安徽省","sales_count":395},{"category_name":"壁挂炉","year":"2017","province_name":"湖北省","sales_count":230},{"category_name":"壁挂炉","year":"2017","province_name":"云南省","sales_count":381},{"category_name":"壁挂炉","year":"2017","province_name":"贵州省","sales_count":203},{"category_name":"壁挂炉","year":"2017","province_name":"黑龙江省","sales_count":251},{"category_name":"壁挂炉","year":"2017","province_name":"陕西省","sales_count":318},{"category_name":"壁挂炉","year":"2017","province_name":"山西省","sales_count":367},{"category_name":"壁挂炉","year":"2017","province_name":"甘肃省","sales_count":355},{"category_name":"壁挂炉","year":"2017","province_name":"上海市","sales_count":393},{"category_name":"壁挂炉","year":"2017","province_name":"天津市","sales_count":352},{"category_name":"壁挂炉","year":"2017","province_name":"山东省","sales_count":222},{"category_name":"壁挂炉","year":"2017","province_name":"四川省","sales_count":352},{"category_name":"壁挂炉","year":"2017","province_name":"广东省","sales_count":303},{"category_name":"壁挂炉","year":"2017","province_name":"浙江省","sales_count":329},{"category_name":"壁挂炉","year":"2017","province_name":"江西省","sales_count":349},{"category_name":"壁挂炉","year":"2017","province_name":"辽宁省","sales_count":317},{"category_name":"壁挂炉","year":"2017","province_name":"河南省","sales_count":249},{"category_name":"壁挂炉","year":"2017","province_name":"吉林省","sales_count":372},{"category_name":"壁挂炉","year":"2017","province_name":"北京市","sales_count":266},{"category_name":"壁挂炉","year":"2017","province_name":"海南省","sales_count":230},{"category_name":"壁挂炉","year":"2017","province_name":"宁夏区","sales_count":309},{"category_name":"壁挂炉","year":"2017","province_name":"西藏区","sales_count":364},{"category_name":"壁挂炉","year":"2017","province_name":"河北省","sales_count":321},{"category_name":"壁挂炉","year":"2017","province_name":"广西壮族自治区","sales_count":334},{"category_name":"冰柜","year":"2017","province_name":"福建省","sales_count":358},{"category_name":"冰柜","year":"2017","province_name":"重庆市","sales_count":343},{"category_name":"冰柜","year":"2017","province_name":"内蒙古","sales_count":316},{"category_name":"冰柜","year":"2017","province_name":"新疆区","sales_count":252},{"category_name":"冰柜","year":"2017","province_name":"青海省","sales_count":220},{"category_name":"冰柜","year":"2017","province_name":"江苏省","sales_count":332},{"category_name":"冰柜","year":"2017","province_name":"湖南省","sales_count":293},{"category_name":"冰柜","year":"2017","province_name":"安徽省","sales_count":233},{"category_name":"冰柜","year":"2017","province_name":"湖北省","sales_count":247},{"category_name":"冰柜","year":"2017","province_name":"云南省","sales_count":237},{"category_name":"冰柜","year":"2017","province_name":"贵州省","sales_count":268},{"category_name":"冰柜","year":"2017","province_name":"黑龙江省","sales_count":286},{"category_name":"冰柜","year":"2017","province_name":"陕西省","sales_count":346},{"category_name":"冰柜","year":"2017","province_name":"山西省","sales_count":324},{"category_name":"冰柜","year":"2017","province_name":"甘肃省","sales_count":266},{"category_name":"冰柜","year":"2017","province_name":"上海市","sales_count":400},{"category_name":"冰柜","year":"2017","province_name":"天津市","sales_count":240},{"category_name":"冰柜","year":"2017","province_name":"山东省","sales_count":258},{"category_name":"冰柜","year":"2017","province_name":"四川省","sales_count":276},{"category_name":"冰柜","year":"2017","province_name":"广东省","sales_count":297},{"category_name":"冰柜","year":"2017","province_name":"浙江省","sales_count":200},{"category_name":"冰柜","year":"2017","province_name":"江西省","sales_count":256},{"category_name":"冰柜","year":"2017","province_name":"辽宁省","sales_count":364},{"category_name":"冰柜","year":"2017","province_name":"河南省","sales_count":216},{"category_name":"冰柜","year":"2017","province_name":"吉林省","sales_count":224},{"category_name":"冰柜","year":"2017","province_name":"北京市","sales_count":322},{"category_name":"冰柜","year":"2017","province_name":"海南省","sales_count":272},{"category_name":"冰柜","year":"2017","province_name":"宁夏区","sales_count":344},{"category_name":"冰柜","year":"2017","province_name":"西藏区","sales_count":223},{"category_name":"冰柜","year":"2017","province_name":"河北省","sales_count":393},{"category_name":"冰柜","year":"2017","province_name":"广西壮族自治区","sales_count":400},{"category_name":"电视","year":"2017","province_name":"上海市","sales_count":221},{"category_name":"电视","year":"2017","province_name":"天津市","sales_count":346},{"category_name":"电视","year":"2017","province_name":"山东省","sales_count":277},{"category_name":"电视","year":"2017","province_name":"四川省","sales_count":289},{"category_name":"电视","year":"2017","province_name":"广东省","sales_count":252},{"category_name":"电视","year":"2017","province_name":"浙江省","sales_count":225},{"category_name":"电视","year":"2017","province_name":"江西省","sales_count":325},{"category_name":"电视","year":"2017","province_name":"辽宁省","sales_count":258},{"category_name":"电视","year":"2017","province_name":"河南省","sales_count":319},{"category_name":"电视","year":"2017","province_name":"吉林省","sales_count":258},{"category_name":"电视","year":"2017","province_name":"北京市","sales_count":212},{"category_name":"电视","year":"2017","province_name":"海南省","sales_count":337},{"category_name":"电视","year":"2017","province_name":"宁夏区","sales_count":264},{"category_name":"电视","year":"2017","province_name":"西藏区","sales_count":203},{"category_name":"电视","year":"2017","province_name":"河北省","sales_count":273},{"category_name":"电视","year":"2017","province_name":"广西壮族自治区","sales_count":398},{"category_name":"电视","year":"2017","province_name":"福建省","sales_count":365},{"category_name":"电视","year":"2017","province_name":"重庆市","sales_count":262},{"category_name":"电视","year":"2017","province_name":"内蒙古","sales_count":322},{"category_name":"电视","year":"2017","province_name":"新疆区","sales_count":297},{"category_name":"电视","year":"2017","province_name":"青海省","sales_count":299},{"category_name":"电视","year":"2017","province_name":"江苏省","sales_count":219},{"category_name":"电视","year":"2017","province_name":"湖南省","sales_count":348},{"category_name":"电视","year":"2017","province_name":"安徽省","sales_count":369},{"category_name":"电视","year":"2017","province_name":"湖北省","sales_count":379},{"category_name":"电视","year":"2017","province_name":"云南省","sales_count":397},{"category_name":"电视","year":"2017","province_name":"贵州省","sales_count":326},{"category_name":"电视","year":"2017","province_name":"黑龙江省","sales_count":250},{"category_name":"电视","year":"2017","province_name":"陕西省","sales_count":342},{"category_name":"电视","year":"2017","province_name":"山西省","sales_count":222},{"category_name":"电视","year":"2017","province_name":"甘肃省","sales_count":221}],"times":null,"pageNumber":0,"pageSize":0,"pageCount":0}